autorunx.py
globals.py
lib/dataio/__init__.py
lib/dataio/dtio-i-bool.py
lib/dataio/dtio-i-float.py
lib/dataio/dtio-i-int.py
lib/dataio/dtio-i-string.py
lib/dataprocess/__init__.py
lib/dataprocess/dtpc-abs.py
lib/dataprocess/dtpc-add.py
lib/dataprocess/dtpc-and.py
lib/dataprocess/dtpc-bool2string.py
lib/dataprocess/dtpc-divide.py
lib/dataprocess/dtpc-eq_number.py
lib/dataprocess/dtpc-eq_string.py
lib/dataprocess/dtpc-ge.py
lib/dataprocess/dtpc-gt.py
lib/dataprocess/dtpc-le.py
lib/dataprocess/dtpc-logical_select_bool.py
lib/dataprocess/dtpc-logical_select_number.py
lib/dataprocess/dtpc-logical_select_string.py
lib/dataprocess/dtpc-lt.py
lib/dataprocess/dtpc-mod.py
lib/dataprocess/dtpc-multiply.py
lib/dataprocess/dtpc-not.py
lib/dataprocess/dtpc-number2string.py
lib/dataprocess/dtpc-or.py
lib/dataprocess/dtpc-subtract.py
lib/eventreceive/__init__.py
lib/eventreceive/evrx-start.py
lib/eventtransmit/__init__.py
lib/eventtransmit/evtx-end.py
lib/flowcontrol/__init__.py
lib/flowcontrol/ctrl-end.py
lib/flowcontrol/ctrl-for.py
lib/flowcontrol/ctrl-if.py
lib/flowcontrol/ctrl-queue.py
lib/flowcontrol/ctrl-select.py
lib/flowcontrol/ctrl-start.py
lib/flowfunction/__init__.py
lib/flowfunction/func-test-1692798936169238-bc2b8ee241bc11ee8331dcf505272cb8-0_0_1.py
lib/system/__init__.py
lib/system/aop.py
lib/system/data_center.py
lib/system/engine.py
lib/system/log.py
lib/system/node_center.py
system/__init__.py
system/aop.py
system/data_center.py
system/engine.py
system/log.py
system/node_center.py
autorunx-1.1.4.dist-info/LICENSE
autorunx-1.1.4.dist-info/METADATA
autorunx-1.1.4.dist-info/WHEEL
autorunx-1.1.4.dist-info/entry_points.txt
autorunx-1.1.4.dist-info/top_level.txt
autorunx-1.1.4.dist-info/RECORD
