Metadata-Version: 2.1
Name: autorunx
Version: 1.1.4
Summary: AutoRunX is an open source low code framework.
Home-page: https://github.com/Xuanfq/AutoRunX-Python
Author: Xuanfq
Author-email: 2624208682@qq.com
License: MIT
Keywords: autorun,auto,run,automatic
Classifier: Development Status :: 3 - Alpha
Classifier: Intended Audience :: Developers
Classifier: Topic :: Software Development :: Build Tools
Classifier: License :: OSI Approved :: MIT License
Classifier: Programming Language :: Python :: 3.9
License-File: LICENSE
